dots/__init__.py
dots/invoice.py
dots/payout_link.py
dots/token.py
dots/transaction.py
dots/user.py
dots_python-1.4.4.dist-info/LICENSE
dots_python-1.4.4.dist-info/METADATA
dots_python-1.4.4.dist-info/WHEEL
dots_python-1.4.4.dist-info/top_level.txt
dots_python-1.4.4.dist-info/RECORD
