Metadata-Version: 2.1
Name: dots-python
Version: 1.4.4
Summary: Add dots checkout to your python app
Home-page: https://dots.dev
Author: Dots.
Author-email: info@senddots.com
Project-URL: Github, https://github.com/Send-Dots/dots-python
Project-URL: Bug Tracker, https://github.com/Send-Dots/dots-python/issues
Classifier: Programming Language :: Python :: 3
Classifier: License :: OSI Approved :: MIT License
Classifier: Operating System :: OS Independent
Requires-Python: >=3.6
License-File: LICENSE
